{"type":"FeatureCollection","features":[{"type":"Feature","id":"1097471470","properties":{"name":"Motor de Sant Pere","height":3},"geometry":{"type":"Polygon","coordinates":[[[-0.162833,39.880084],[-0.162705,39.880241],[-0.162588,39.880191],[-0.16269,39.880033],[-0.162833,39.880084]]]}},{"type":"Feature","id":"1097471471","properties":{"name":"Motor de Sant Rafel","height":3},"geometry":{"type":"Polygon","coordinates":[[[-0.15819,39.882827],[-0.158105,39.882934],[-0.157992,39.882889],[-0.158062,39.882774],[-0.15819,39.882827]]]}}]}